README.rst
dir2json.py
setup.py
dir2json.egg-info/PKG-INFO
dir2json.egg-info/SOURCES.txt
dir2json.egg-info/dependency_links.txt
dir2json.egg-info/entry_points.txt
dir2json.egg-info/requires.txt
dir2json.egg-info/top_level.txt