Metadata-Version: 1.0
Name: dir2json
Version: 0.1.0
Summary: creates a json tree from a directory structure
Home-page: UNKNOWN
Author: David Keijser
Author-email: keijser@gmail.com
License: MIT
Platform: UNKNOWN
